tasting/__init__.py
tasting/decorators.py
tasting/pytest.py
tasting-0.0.1.dist-info/LICENSE
tasting-0.0.1.dist-info/METADATA
tasting-0.0.1.dist-info/WHEEL
tasting-0.0.1.dist-info/top_level.txt
tasting-0.0.1.dist-info/RECORD
